MANIFEST.in
README.rst
requirements.txt
setup.cfg
setup.py
versioneer.py
bin/odo
docs/source/add-new-backend.rst
docs/source/aws.rst
docs/source/csv.rst
docs/source/datashape.rst
docs/source/drop.rst
docs/source/functions.rst
docs/source/hdf5.rst
docs/source/hdfs.rst
docs/source/hive.rst
docs/source/index.rst
docs/source/json.rst
docs/source/mongo.rst
docs/source/overview.rst
docs/source/perf.rst
docs/source/project-info.rst
docs/source/releases.rst
docs/source/sas.rst
docs/source/spark.rst
docs/source/sql.rst
docs/source/ssh.rst
docs/source/type-modifiers.rst
docs/source/uri.rst
odo/__init__.py
odo/_version.py
odo/append.py
odo/chunks.py
odo/compatibility.py
odo/convert.py
odo/core.py
odo/create.py
odo/directory.py
odo/dot.py
odo/drop.py
odo/into.py
odo/numpy_dtype.py
odo/odo.py
odo/regex.py
odo/resource.py
odo/temp.py
odo/utils.py
odo.egg-info/PKG-INFO
odo.egg-info/SOURCES.txt
odo.egg-info/dependency_links.txt
odo.egg-info/not-zip-safe
odo.egg-info/pbr.json
odo.egg-info/requires.txt
odo.egg-info/top_level.txt
odo/backends/__init__.py
odo/backends/aws.py
odo/backends/bcolz.py
odo/backends/bokeh.py
odo/backends/csv.py
odo/backends/dask.py
odo/backends/dynd.py
odo/backends/h5py.py
odo/backends/hdfs.py
odo/backends/hdfstore.py
odo/backends/json.py
odo/backends/mongo.py
odo/backends/pandas.py
odo/backends/pytables.py
odo/backends/sas.py
odo/backends/spark.py
odo/backends/sparksql.py
odo/backends/sql.py
odo/backends/sql_csv.py
odo/backends/ssh.py
odo/backends/text.py
odo/backends/url.py
odo/backends/tests/__init__.py
odo/backends/tests/airline.sas7bdat
odo/backends/tests/conftest.py
odo/backends/tests/dummydata.csv
odo/backends/tests/encoding.csv
odo/backends/tests/test_aws.py
odo/backends/tests/test_bcolz.py
odo/backends/tests/test_bokeh.py
odo/backends/tests/test_csv.py
odo/backends/tests/test_dask_array.py
odo/backends/tests/test_dask_bag.py
odo/backends/tests/test_dynd.py
odo/backends/tests/test_h5py.py
odo/backends/tests/test_hdfs.py
odo/backends/tests/test_hdfstore.py
odo/backends/tests/test_json.py
odo/backends/tests/test_mongo.py
odo/backends/tests/test_mysql.py
odo/backends/tests/test_pandas.py
odo/backends/tests/test_postgres.py
