Metadata-Version: 1.0
Name: odo
Version: 0.3.4
Summary: Data migration utilities
Home-page: https://github.com/blaze/odo
Author: Blaze development team
Author-email: blaze-dev@continuum.io
License: BSD
Keywords: odo data conversion hdf5 sql blaze
Platform: UNKNOWN
